twacapic/__init__.py
twacapic/auth.py
twacapic/collect.py
twacapic/main.py
twacapic/notifications.py
twacapic/templates/__init__.py
twacapic/templates/group_config.yaml
twacapic/templates/min_group_config.yaml
twacapic/utils.py
twacapic-0.8.1.2.dist-info/entry_points.txt
twacapic-0.8.1.2.dist-info/LICENSE
twacapic-0.8.1.2.dist-info/WHEEL
twacapic-0.8.1.2.dist-info/METADATA
twacapic-0.8.1.2.dist-info/RECORD
