Metadata-Version: 2.1
Name: twacapic
Version: 0.8.1.2
Summary: A Twitter Academic API Client
Home-page: https://github.com/Leibniz-HBI/twacapic
License: MIT
Author: Felix Victor Münch
Author-email: f.muench@leibniz-hbi.de
Requires-Python: >=3.8,<4.0
Classifier: Development Status :: 4 - Beta
Classifier: Environment :: Console
Classifier: Intended Audience :: Science/Research
Classifier: License :: OSI Approved :: MIT License
Classifier: Programming Language :: Python :: 3
Classifier: Programming Language :: Python :: 3.8
Classifier: Programming Language :: Python :: 3.9
Classifier: Programming Language :: Python :: 3.10
Classifier: Programming Language :: Python :: 3.11
Requires-Dist: PyYAML (>=5.4.1,<6.0.0)
Requires-Dist: TwitterAPI (>=2.6.9,<3.0.0)
Requires-Dist: loguru (>=0.5.3,<0.6.0)
Requires-Dist: schedule (>=1.0.0,<2.0.0)
Requires-Dist: yagmail (>=0.14.245,<0.15.0)
Project-URL: Repository, https://github.com/Leibniz-HBI/twacapic
